dptools/i2e/__init__.py
dptools/i2e/__main__.py
dptools/i2e/edb.py
dptools/i2e/get_failed.py
dptools/i2e/internal_to_external.py
dptools/i2e/log.py
dptools/i2e/pg.py
dptools/i2e/req.py
dptools/i2e/structs.py
dptools_i2e-1.0.0.dist-info/METADATA
dptools_i2e-1.0.0.dist-info/WHEEL
dptools_i2e-1.0.0.dist-info/entry_points.txt
dptools_i2e-1.0.0.dist-info/top_level.txt
dptools_i2e-1.0.0.dist-info/RECORD
