Metadata-Version: 2.1
Name: dptools-i2e
Version: 1.0.0
Summary: Hack normal objects into external objects
Author-email: deepfos-python-team <deepfos_py@deepfinance.com>
License: MIT License
Classifier: Programming Language :: Python :: 3.8
Requires-Python: >=3.8
Requires-Dist: edgedb ==1.4.0
Requires-Dist: psycopg2-binary ==2.9.9
